<?xml version="1.0" encoding="UTF-8"?>
<kcfg xmlns="http://www.kde.org/standards/kcfg/1.0"
      xmlns:xsi="http://www.w3.org/2001/XMLSchema-instance"
      xsi:schemaLocation="http://www.kde.org/standards/kcfg/1.0
      http://www.kde.org/standards/kcfg/1.0/kcfg.xsd" >
  <kcfgfile name=""/>
 
  <group name="Configurate">
    <entry name="latitude" type="String">
      <default>0.0</default>
    </entry>
    <entry name="longitude" type="String">
      <default>0.0</default>
    </entry>
    <entry name="dayTemperature" type="String">
      <default>0.0</default>
    </entry>
    <entry name="nightTemperature" type="String">
      <default>3000</default>
    </entry>
    <entry name="brightness" type="String">
      <default>1</default>
    </entry>
    <entry name="gammaR" type="String">
      <default>0.00</default>
    </entry>
    <entry name="gammaG" type="String">
      <default>0.00</default>
    </entry>
    <entry name="gammaB" type="String">
        <default>0.00</default>
    </entry>
    <entry name="smoothTransition" type="Bool">
      <default>true</default>
    </entry>
    <entry name="autoStart" type="Bool">
      <default>false</default>
    </entry>
    <entry name="method" type="String">
      <default>Auto</default>
    </entry>
  </group>
 
</kcfg>